ramdisk/README.MD
ramdisk/__init__.py
ramdisk/files.cab
ramdisk/install_imdisk.bat
ramdisk/requirements.txt
ramdisk/thirdparty.json
ramdisk-0.10.dist-info/LICENSE.rst
ramdisk-0.10.dist-info/METADATA
ramdisk-0.10.dist-info/WHEEL
ramdisk-0.10.dist-info/top_level.txt
ramdisk-0.10.dist-info/RECORD
