Metadata-Version: 2.1
Name: ramdisk
Version: 0.10
Summary: A collection of functions that interact with the imdisk.exe utility
Home-page: https://github.com/hansalemaos/ramdisk
Author: Johannes Fischer
Author-email: aulasparticularesdealemaosp@gmail.com
License: MIT
Keywords: imdisk,files
Classifier: Development Status :: 4 - Beta
Classifier: Programming Language :: Python :: 3 :: Only
Classifier: Programming Language :: Python :: 3.10
Classifier: Topic :: Software Development :: Libraries :: Python Modules
Classifier: Topic :: Utilities
License-File: LICENSE.rst
Requires-Dist: getfilenuitkapython
